inkaterm/__init__.py
inkaterm/procces/__init__.py
inkaterm/procces/reader.py
inkaterm/report/__init__.py
inkaterm/report/panelRead.py
inkaterm-1.2.1.dist-info/METADATA
inkaterm-1.2.1.dist-info/WHEEL
inkaterm-1.2.1.dist-info/top_level.txt
inkaterm-1.2.1.dist-info/RECORD
