Metadata-Version: 2.4
Name: inkaterm
Version: 1.2.1
Summary: Convert PNG images to ASCII colored art
Author: redstar1228
Author-email: aliakbarzarei41@gmail.com
Requires-Python: >=3.6
Requires-Dist: termcolor
Requires-Dist: pillow
Dynamic: author
Dynamic: author-email
Dynamic: requires-dist
Dynamic: requires-python
Dynamic: summary
